okami/__init__.py
okami/api.py
okami/cli.py
okami/constants.py
okami/engine.py
okami/example.py
okami/exceptions.py
okami/loader.py
okami/middleware.py
okami/pipeline.py
okami/server.py
okami/signals.py
okami/storage.py
okami/utils.py
okami/cfg/__init__.py
okami/cfg/default.py
okami/cfg/example.py
okami-0.2.0.dist-info/LICENSE.txt
okami-0.2.0.dist-info/METADATA
okami-0.2.0.dist-info/RECORD
okami-0.2.0.dist-info/WHEEL
okami-0.2.0.dist-info/entry_points.txt
okami-0.2.0.dist-info/top_level.txt
