Metadata-Version: 2.1
Name: okami
Version: 0.2.0
Summary: A high-level web scraping framework
Home-page: https://github.com/ambrozic/okami
Author: ambrozic
Author-email: ambrozic@gmail.com
Maintainer: ambrozic
Maintainer-email: ambrozic@gmail.com
License: BSD
Project-URL: Code, https://github.com/ambrozic/okami
Project-URL: Documentation, https://ambrozic.github.io/okami
Keywords: scraping framework
Platform: UNKNOWN
Classifier: Programming Language :: Python
Classifier: Environment :: Web Environment
Classifier: Operating System :: MacOS :: MacOS X
Classifier: Operating System :: POSIX
Classifier: License :: OSI Approved :: BSD License
Classifier: Programming Language :: Python :: 3
Classifier: Programming Language :: Python :: 3.6
Classifier: Programming Language :: Python :: 3.7
Classifier: Topic :: Internet
Classifier: Topic :: Software Development :: Libraries :: Application Frameworks
Classifier: Topic :: Software Development :: Libraries :: Python Modules
Classifier: Intended Audience :: Developers
Requires-Python: >=3.6
Provides-Extra: docs
Provides-Extra: tests
Requires-Dist: aiohttp (<4.0,>=3.2.0)
Requires-Dist: attrs (<19.0,>=18.1.0)
Requires-Dist: click (<7.0,>=6.0)
Requires-Dist: lxml (<5.0,>=4.0)
Requires-Dist: multidict (<5.0,>=4.0)
Requires-Dist: sqlitedict (<1.6,>=1.5)
Provides-Extra: docs
Requires-Dist: mkdocs-material (==3.0.3); extra == 'docs'
Requires-Dist: mkdocs (==1.0.1); extra == 'docs'
Requires-Dist: pygments (==2.2.0); extra == 'docs'
Requires-Dist: pymdown-extensions (==4.12); extra == 'docs'
Provides-Extra: tests
Requires-Dist: codecov (==2.0.15); extra == 'tests'
Requires-Dist: flake8 (==3.5.0); extra == 'tests'
Requires-Dist: markupsafe (==1.0); extra == 'tests'
Requires-Dist: pipdeptree (==0.13.0); extra == 'tests'
Requires-Dist: pytest-asyncio (==0.9.0); extra == 'tests'
Requires-Dist: pytest-cov (==2.5.1); extra == 'tests'
Requires-Dist: pytest-freezegun (==0.2.0); extra == 'tests'
Requires-Dist: pytest (==3.7.1); extra == 'tests'
Requires-Dist: pyyaml (==3.13); extra == 'tests'
